[
    {
        "type": "gps",
        "name": "location",
        "label": "Location"
    },
    {
        "type": "integer",
        "min": 5,
        "max": 10,
        "default": 1,
        "name": "num",
        "label": "Number from 5 to 10"
    },
    {
        "type": "text",
        "name": "description",
        "label": "Description"
    },
    {
        "type": "choice",
        "name": "pick",
        "label": "Pick one",
        "choices": [
            ["choice1", "Banana"],
            ["choice2", "Apple"],
            ["choice3", "Pear"]
        ]
    },
    {
        "type": "image",
        "name": "image",
        "label": "Picture"
    }
]